racers_report/__init__.py
racers_report/__main__.py
racers_report/report_generator.py
racers_report/data/abbreviations.txt
racers_report/data/end.log
racers_report/data/start.log
f1_racers_report-1.0.8.dist-info/LICENSE
f1_racers_report-1.0.8.dist-info/METADATA
f1_racers_report-1.0.8.dist-info/WHEEL
f1_racers_report-1.0.8.dist-info/top_level.txt
f1_racers_report-1.0.8.dist-info/RECORD
