Metadata-Version: 2.1
Name: f1-racers-report
Version: 1.0.8
Summary: Application that generates the report from provided files
Home-page: https://github.com/stefanyuk/racing-report
Author: Andriy Stefanyuk
Author-email: andriy11143@gmail.com
License: UNKNOWN
Project-URL: Issue Tracker, https://github.com/stefanyuk/racing-report/issues
Keywords: packaging,resources
Platform: UNKNOWN
Classifier: Programming Language :: Python :: 3
Classifier: License :: OSI Approved :: MIT License
Classifier: Operating System :: OS Independent
License-File: LICENSE
Requires-Dist: colorama
